llama_index/packs/sentence_window_retriever/__init__.py
llama_index/packs/sentence_window_retriever/base.py
llama_index_packs_sentence_window_retriever-0.5.1.dist-info/METADATA
llama_index_packs_sentence_window_retriever-0.5.1.dist-info/WHEEL
llama_index_packs_sentence_window_retriever-0.5.1.dist-info/licenses/LICENSE
llama_index_packs_sentence_window_retriever-0.5.1.dist-info/RECORD
