Metadata-Version: 2.4
Name: llama-index-packs-sentence-window-retriever
Version: 0.5.1
Summary: llama-index packs sentence_window_retriever integration
Author-email: Your Name <you@example.com>
Maintainer: jerryjliu
License-Expression: MIT
License-File: LICENSE
Keywords: retriever,sentence,window
Requires-Python: <4.0,>=3.9
Requires-Dist: llama-index-core<0.15,>=0.13.0
Requires-Dist: llama-index-embeddings-huggingface<0.7,>=0.6.0
Requires-Dist: llama-index-llms-openai<0.6,>=0.5.0
